Metadata-Version: 2.2
Name: twikit
Version: 2.3.2
Summary: Twitter API wrapper for python with **no API key required**.
Home-page: https://github.com/d60/twikit
License: MIT
Requires-Python: >=3.8
License-File: LICENSE
Requires-Dist: httpx[socks]
Requires-Dist: filetype
Requires-Dist: beautifulsoup4
Requires-Dist: pyotp
Requires-Dist: lxml
Requires-Dist: webvtt-py
Requires-Dist: m3u8
Requires-Dist: Js2Py-3.13
Dynamic: description
Dynamic: description-content-type
Dynamic: home-page
Dynamic: license
Dynamic: requires-dist
Dynamic: requires-python
Dynamic: summary
